aiida_environ/__init__.py
aiida_environ/calculations/__init__.py
aiida_environ/calculations/finite.py
aiida_environ/calculations/partial.py
aiida_environ/calculations/pw.py
aiida_environ/calculations/adsorbate/__init__.py
aiida_environ/calculations/adsorbate/gen_multitype.py
aiida_environ/calculations/adsorbate/gen_supercell.py
aiida_environ/calculations/adsorbate/post_supercell.py
aiida_environ/data/__init__.py
aiida_environ/data/charge.py
aiida_environ/parsers/__init__.py
aiida_environ/parsers/pw.py
aiida_environ/parsers/parse_raw/__init__.py
aiida_environ/parsers/parse_raw/pw.py
aiida_environ/utils/__init__.py
aiida_environ/utils/charge.py
aiida_environ/utils/environ.py
aiida_environ/utils/graph.py
aiida_environ/utils/mapping.py
aiida_environ/utils/occupancy.py
aiida_environ/utils/vector.py
aiida_environ/workflows/__init__.py
aiida_environ/workflows/pw/__init__.py
aiida_environ/workflows/pw/base.py
aiida_environ/workflows/pw/force_test.py
aiida_environ/workflows/pw/grandcanonical.py
aiida_environ/workflows/pw/graphml.py
aiida_environ/workflows/pw/parameterization.py
aiida_environ/workflows/pw/relax.py
aiida_environ/workflows/pw/solvation.py
aiida_environ-1.0.0.dist-info/entry_points.txt
aiida_environ-1.0.0.dist-info/LICENSE.txt
aiida_environ-1.0.0.dist-info/WHEEL
aiida_environ-1.0.0.dist-info/METADATA
aiida_environ-1.0.0.dist-info/RECORD
